mdformat_obsidian/__init__.py
mdformat_obsidian/plugin.py
mdformat_obsidian/py.typed
mdformat_obsidian/factories/__init__.py
mdformat_obsidian/factories/_obsidian_blockquote_factories.py
mdformat_obsidian/mdit_plugins/__init__.py
mdformat_obsidian/mdit_plugins/_obsidian_callouts.py
mdformat_obsidian/mdit_plugins/_obsidian_inline_footnotes.py
mdformat_obsidian/mdit_plugins/_obsidian_task_lists.py
mdformat_obsidian-0.1.0.dist-info/entry_points.txt
mdformat_obsidian-0.1.0.dist-info/LICENSE
mdformat_obsidian-0.1.0.dist-info/WHEEL
mdformat_obsidian-0.1.0.dist-info/METADATA
mdformat_obsidian-0.1.0.dist-info/RECORD
