Metadata-Version: 2.1
Name: mdformat_obsidian
Version: 0.1.0
Summary: An mdformat plugin for `obsidian`.
Keywords: markdown,markdown-it,mdformat,mdformat_plugin_template
Author-email: kyleking <dev.act.kyle@gmail.com>
Requires-Python: >=3.8.5
Classifier: Intended Audience :: Developers
Classifier: License :: OSI Approved :: MIT License
Classifier: Programming Language :: Python :: 3
Classifier: Topic :: Software Development :: Libraries :: Python Modules
Requires-Dist: mdformat >= 0.7.17
Requires-Dist: mdformat-gfm >= 0.3.6
Requires-Dist: mdit-py-plugins >= 0.4.1
Requires-Dist: pre-commit ; extra == "dev"
Requires-Dist: mdformat-beautysh >= 0.1.1 ; extra == "recommended"
Requires-Dist: mdformat-config >= 0.1.3 ; extra == "recommended"
Requires-Dist: mdformat-frontmatter >= 2.0.8 ; extra == "recommended"
Requires-Dist: mdformat-ruff >= 0.1.3 ; extra == "recommended"
Requires-Dist: mdformat-simple-breaks >= 0.0.1 ; extra == "recommended"
Requires-Dist: mdformat-tables >= 0.4.1 ; extra == "recommended"
Requires-Dist: mdformat-web >= 0.1.0 ; extra == "recommended"
Requires-Dist: mdformat-wikilink >= 0.2.0 ; extra == "recommended"
Requires-Dist: setuptools ; extra == "recommended"
Requires-Dist: pytest >= 7.4.4 ; extra == "test"
Requires-Dist: pytest-beartype >= 0.0.2 ; extra == "test"
Requires-Dist: pytest-cov >= 4.1.0 ; extra == "test"
Project-URL: Bug Tracker, https://github.com/kyleking/mdformat-obsidian/issues
Project-URL: Changelog, https://github.com/kyleking/mdformat-obsidian/releases
Project-URL: homepage, https://github.com/kyleking/mdformat-obsidian
Provides-Extra: dev
Provides-Extra: recommended
Provides-Extra: test
